dql/__init__.py
dql/cli.py
dql/engine.py
dql/exceptions.py
dql/help.py
dql/history.py
dql/models.py
dql/monitor.py
dql/output.py
dql/throttle.py
dql/util.py
dql/expressions/__init__.py
dql/expressions/base.py
dql/expressions/constraint.py
dql/expressions/selection.py
dql/expressions/update.py
dql/expressions/visitor.py
dql/grammar/__init__.py
dql/grammar/common.py
dql/grammar/parsed_primitives.py
dql/grammar/query.py
tests/snapshots/__init__.py
tests/snapshots/snap_test_cli.py
dql-0.6.2.dist-info/LICENSE
dql-0.6.2.dist-info/METADATA
dql-0.6.2.dist-info/WHEEL
dql-0.6.2.dist-info/entry_points.txt
dql-0.6.2.dist-info/top_level.txt
dql-0.6.2.dist-info/RECORD
