Metadata-Version: 2.1
Name: dql
Version: 0.6.2
Summary: DynamoDB Query Language
Home-page: http://github.com/stevearc/dql
Author: Steven Arcangeli
Author-email: stevearc@stevearc.com
License: MIT
Keywords: aws dynamo dynamodb sql
Platform: any
Classifier: Development Status :: 4 - Beta
Classifier: Intended Audience :: Developers
Classifier: License :: OSI Approved :: MIT License
Classifier: Operating System :: OS Independent
Classifier: Programming Language :: Python
Classifier: Programming Language :: Python :: 3
Classifier: Programming Language :: Python :: 3.6
Classifier: Programming Language :: Python :: 3.7
Classifier: Programming Language :: Python :: 3.8
Requires-Python: >=3.6
License-File: LICENSE
Requires-Dist: dynamo3 (>=1.0.0)
Requires-Dist: pyparsing (==2.1.4)
Requires-Dist: python-dateutil
Requires-Dist: botocore (>=1.17.55)
Requires-Dist: rich (>=6.1.1)
Requires-Dist: typing-extensions
